{
  "lang":"en",
  "name":"pipeline",
  "version":"0.0.0",
  "spacy_version":">=3.7.2,<3.8.0",
  "description":"",
  "author":"",
  "email":"",
  "url":"",
  "license":"",
  "spacy_git_version":"a89eae928",
  "vectors":{
    "width":0,
    "vectors":0,
    "keys":0,
    "name":null,
    "mode":"default"
  },
  "labels":{
    "tok2vec":[

    ],
    "ner":[
      "RECORDING_DATE"
    ]
  },
  "pipeline":[
    "tok2vec",
    "ner"
  ],
  "components":[
    "tok2vec",
    "ner"
  ],
  "disabled":[

  ],
  "performance":{
    "ents_f":0.0,
    "ents_p":0.0,
    "ents_r":0.0,
    "ents_per_type":{
      "GRANTOR":{
        "p":0.0,
        "r":0.0,
        "f":0.0
      }
    },
    "tok2vec_loss":0.0,
    "ner_loss":680.6538669467
  }
}